ScenarioHeatMap/SHM.py
ScenarioHeatMap/__init__.py
ScenarioHeatMap-1.2.2.dist-info/METADATA
ScenarioHeatMap-1.2.2.dist-info/WHEEL
ScenarioHeatMap-1.2.2.dist-info/top_level.txt
ScenarioHeatMap-1.2.2.dist-info/RECORD
