Metadata-Version: 2.1
Name: ScenarioHeatMap
Version: 1.2.2
Summary: 用于制作简易热力图的模块
Home-page: UNKNOWN
Author: yu.han
Author-email: amazinghenry@qq.com
License: UNKNOWN
Platform: UNKNOWN
Classifier: Programming Language :: Python :: 3
Classifier: License :: OSI Approved :: MIT License
Classifier: Operating System :: OS Independent
Requires-Python: >=3
Requires-Dist: opencv-python
Requires-Dist: Pillow
Requires-Dist: matplotlib
Requires-Dist: numpy
